SalesforcePy/__init__.py
SalesforcePy/chatter.py
SalesforcePy/commons.py
SalesforcePy/device_flow.py
SalesforcePy/jobs.py
SalesforcePy/sfdc.py
SalesforcePy/wave.py
SalesforcePy/einstein/__init__.py
SalesforcePy/einstein/llm/__init__.py
SalesforcePy/einstein/llm/embeddings.py
SalesforcePy/einstein/llm/prompt.py
salesforcepy-2.2.1.dist-info/licenses/LICENSE
salesforcepy-2.2.1.dist-info/METADATA
salesforcepy-2.2.1.dist-info/WHEEL
salesforcepy-2.2.1.dist-info/top_level.txt
salesforcepy-2.2.1.dist-info/RECORD
