Metadata-Version: 2.4
Name: SalesforcePy
Version: 2.2.1
Summary: An absurdly simple package for making Salesforce Rest API requests
Home-page: https://github.com/forcedotcom/SalesforcePy
Author: Aaron Caffrey
Author-email: acaffrey@salesforce.com
License: BSD
Classifier: Programming Language :: Python :: 3
Classifier: License :: OSI Approved :: BSD License
Classifier: Operating System :: OS Independent
License-File: LICENSE
Requires-Dist: requests<3,>=2.20.0
Dynamic: author
Dynamic: author-email
Dynamic: classifier
Dynamic: description
Dynamic: description-content-type
Dynamic: home-page
Dynamic: license
Dynamic: license-file
Dynamic: requires-dist
Dynamic: summary
